pyspiflash-0.6.5.dist-info/licenses/LICENSE
spiflash/__init__.py
spiflash/serialflash.py
pyspiflash-0.6.5.dist-info/METADATA
pyspiflash-0.6.5.dist-info/WHEEL
pyspiflash-0.6.5.dist-info/top_level.txt
pyspiflash-0.6.5.dist-info/RECORD
