Metadata-Version: 2.4
Name: pyspiflash
Version: 0.6.5
Summary: SPI data flash device drivers (pure Python)
Home-page: http://github.com/eblot/pyspiflash
Author: Emmanuel Blot
Author-email: emmanuel.blot@free.fr
Maintainer: Emmanuel Blot
Maintainer-email: emmanuel.blot@free.fr
License: MIT
Keywords: driver,ftdi,usb,spi,flash,mtd
Classifier: Development Status :: 4 - Beta
Classifier: Environment :: Other Environment
Classifier: Natural Language :: English
Classifier: Intended Audience :: Developers
Classifier: License :: OSI Approved :: MIT License
Classifier: Operating System :: MacOS :: MacOS X
Classifier: Operating System :: POSIX
Classifier: Operating System :: Microsoft :: Windows
Classifier: Programming Language :: Python :: 3.5
Classifier: Programming Language :: Python :: 3.6
Classifier: Programming Language :: Python :: 3.7
Classifier: Programming Language :: Python :: 3.8
Classifier: Topic :: Software Development :: Libraries :: Python Modules
Classifier: Topic :: System :: Hardware :: Hardware Drivers
Requires-Python: >=3.5
License-File: LICENSE
Requires-Dist: pyftdi<0.60,>=0.42
Dynamic: author
Dynamic: author-email
Dynamic: classifier
Dynamic: description
Dynamic: home-page
Dynamic: keywords
Dynamic: license
Dynamic: license-file
Dynamic: maintainer
Dynamic: maintainer-email
Dynamic: requires-dist
Dynamic: requires-python
Dynamic: summary
